django_admin_bootstrapped/__init__.py
django_admin_bootstrapped/models.py
django_admin_bootstrapped/renderers.py
django_admin_bootstrapped/runtests.py
django_admin_bootstrapped/tests.py
django_admin_bootstrapped/widgets.py
django_admin_bootstrapped/admin/__init__.py
django_admin_bootstrapped/admin/models.py
django_admin_bootstrapped/static/admin/css/admin-inlines.css
django_admin_bootstrapped/static/admin/css/changelists.css
django_admin_bootstrapped/static/admin/css/overrides.css
django_admin_bootstrapped/static/admin/js/generic-lookup.js
django_admin_bootstrapped/static/admin/js/jquery-1.9.1.min.js
django_admin_bootstrapped/static/admin/js/jquery-migrate-1.2.1.min.js
django_admin_bootstrapped/static/admin/js/jquery.sortable.js
django_admin_bootstrapped/static/bootstrap/css/bootstrap-theme.css
django_admin_bootstrapped/static/bootstrap/css/bootstrap-theme.css.map
django_admin_bootstrapped/static/bootstrap/css/bootstrap-theme.min.css
django_admin_bootstrapped/static/bootstrap/css/bootstrap.css
django_admin_bootstrapped/static/bootstrap/css/bootstrap.css.map
django_admin_bootstrapped/static/bootstrap/css/bootstrap.min.css
django_admin_bootstrapped/static/bootstrap/fonts/glyphicons-halflings-regular.eot
django_admin_bootstrapped/static/bootstrap/fonts/glyphicons-halflings-regular.svg
django_admin_bootstrapped/static/bootstrap/fonts/glyphicons-halflings-regular.ttf
django_admin_bootstrapped/static/bootstrap/fonts/glyphicons-halflings-regular.woff
django_admin_bootstrapped/static/bootstrap/fonts/glyphicons-halflings-regular.woff2
django_admin_bootstrapped/static/bootstrap/js/bootstrap.js
django_admin_bootstrapped/static/bootstrap/js/bootstrap.min.js
django_admin_bootstrapped/static/bootstrap-rtl/css/bootstrap-flipped.css
django_admin_bootstrapped/static/bootstrap-rtl/css/bootstrap-flipped.css.map
django_admin_bootstrapped/static/bootstrap-rtl/css/bootstrap-flipped.min.css
django_admin_bootstrapped_ivc-2.5.7.6.dist-info/METADATA
django_admin_bootstrapped_ivc-2.5.7.6.dist-info/RECORD
django_admin_bootstrapped_ivc-2.5.7.6.dist-info/WHEEL
django_admin_bootstrapped_ivc-2.5.7.6.dist-info/top_level.txt
