Metadata-Version: 2.1
Name: django-admin-bootstrapped-ivc
Version: 2.5.7.6
Summary: A Bootstrap theme for Django Admin
Home-page: https://github.com/ivc-inform/django-admin-bootstrapped.git
Author: Riccardo Forina
Author-email: riccardo@forina.me
Maintainer: Riccardo Magliocchetti
Maintainer-email: riccardo.magliocchetti@gmail.com
License: BSD License
Platform: OS Independent
Classifier: Development Status :: 5 - Production/Stable
Classifier: Environment :: Web Environment
Classifier: Framework :: Django
Classifier: Intended Audience :: Developers
Classifier: License :: OSI Approved :: BSD License
Classifier: Operating System :: OS Independent
Classifier: Programming Language :: Python
Classifier: Programming Language :: Python :: 2
Classifier: Programming Language :: Python :: 3
Classifier: Topic :: Internet :: WWW/HTTP :: Dynamic Content
Classifier: Topic :: Software Development
Classifier: Topic :: Software Development :: Libraries :: Application Frameworks
Requires-Dist: setuptools
Requires-Dist: Django (>=1.11.15)
